customersatisfactionmetrics/__init__.py
customersatisfactionmetrics/__main__.py
customersatisfactionmetrics/admin.py
customersatisfactionmetrics/apps.py
customersatisfactionmetrics/defaults.py
customersatisfactionmetrics/urls.py
customersatisfactionmetrics/views.py
customersatisfactionmetrics/forms/__init__.py
customersatisfactionmetrics/forms/survey_form.py
customersatisfactionmetrics/migrations/0001_initial.py
customersatisfactionmetrics/migrations/0002_alter_response_response_type.py
customersatisfactionmetrics/migrations/0003_alter_question_options_question_order.py
customersatisfactionmetrics/migrations/0004_question_is_required.py
customersatisfactionmetrics/migrations/0005_response_session_id.py
customersatisfactionmetrics/migrations/0006_question_max_label_question_min_label.py
customersatisfactionmetrics/migrations/0007_question_language.py
customersatisfactionmetrics/migrations/0008_response_created_at_response_updated_at_and_more.py
customersatisfactionmetrics/migrations/__init__.py
customersatisfactionmetrics/models/__init__.py
customersatisfactionmetrics/models/questions.py
customersatisfactionmetrics/models/responses.py
customersatisfactionmetrics/models/surveys.py
customersatisfactionmetrics/templates/survey_form.html
customersatisfactionmetrics/templates/thank_you.html
customersatisfactionmetrics/templatetags/__init__.py
customersatisfactionmetrics/templatetags/survey_tags.py
customersatisfactionmetrics/tests/__init__.py
customersatisfactionmetrics/tests/base_tests.py
customersatisfactionmetrics/tests/test_forms.py
customersatisfactionmetrics/tests/test_models.py
customersatisfactionmetrics/tests/test_utils.py
customersatisfactionmetrics/tests/test_views.py
customersatisfactionmetrics/views/__init__.py
customersatisfactionmetrics/views/survey_view.py
customersatisfactionmetrics/views/thank_you_view.py
customersatisfactionmetrics-1.0.9.dist-info/LICENSE
customersatisfactionmetrics-1.0.9.dist-info/METADATA
customersatisfactionmetrics-1.0.9.dist-info/WHEEL
customersatisfactionmetrics-1.0.9.dist-info/top_level.txt
customersatisfactionmetrics-1.0.9.dist-info/RECORD
