Metadata-Version: 2.2
Name: customersatisfactionmetrics
Version: 1.0.9
Summary: A short description of your package
Home-page: http://github.com/pescheckit/customersatisfactionmetrics
Author: Bram Mittendorff
Author-email: bram@pescheck.io
License: MIT
Keywords: django,survey,customer satisfaction,feedback,CSAT,NPS,CES,survey management,user responses,analytics,data collection,web surveys,survey application,docker,docker compose,web app,user experience,user feedback,questionnaire,user engagement,metadata tracking,response analysis,Django application
Classifier: Development Status :: 5 - Production/Stable
Classifier: Natural Language :: English
Classifier: Topic :: Utilities
Classifier: Environment :: Web Environment
Classifier: Intended Audience :: Developers
Classifier: License :: OSI Approved :: MIT License
Classifier: Operating System :: OS Independent
Classifier: Programming Language :: Python :: 3
Classifier: Programming Language :: Python :: 3.7
Classifier: Programming Language :: Python :: 3.8
Classifier: Programming Language :: Python :: 3.9
Classifier: Framework :: Django
License-File: LICENSE
Requires-Dist: Django>=3.0
Dynamic: author
Dynamic: author-email
Dynamic: classifier
Dynamic: description
Dynamic: description-content-type
Dynamic: home-page
Dynamic: keywords
Dynamic: license
Dynamic: requires-dist
Dynamic: summary
